LICENSE
README.md
setup.py
chronnos/__init__.py
chronnos/predict.py
chronnos/train_chronnos.py
chronnos.egg-info/PKG-INFO
chronnos.egg-info/SOURCES.txt
chronnos.egg-info/dependency_links.txt
chronnos.egg-info/requires.txt
chronnos.egg-info/top_level.txt
chronnos/data/__init__.py
chronnos/data/convert.py
chronnos/data/download.py
chronnos/data/generator.py
chronnos/evaluate/__init__.py
chronnos/evaluate/detect.py
chronnos/train/__init__.py
chronnos/train/callback.py
chronnos/train/metric.py
chronnos/train/model.py