Metadata-Version: 2.1
Name: chronnos
Version: 1.0.0
Summary: CHRONNOS
Home-page: https://github.com/RobertJaro/MultiChannelCHDetection
Author: Robert Jarolim
Author-email: robert.jarolim@uni-graz.at
License: GPL-3.0
Platform: UNKNOWN
License-File: LICENSE
